django_elo_rating/__init__.py
django_elo_rating/models.py
django_elo_rating-0.0.1.dist-info/LICENSE
django_elo_rating-0.0.1.dist-info/METADATA
django_elo_rating-0.0.1.dist-info/WHEEL
django_elo_rating-0.0.1.dist-info/top_level.txt
django_elo_rating-0.0.1.dist-info/RECORD
