Metadata-Version: 2.1
Name: django-elo-rating
Version: 0.0.1
Summary: ELO-Ratings for your django models
Home-page: https://git.fritsch.co/open-source/django_elo_rating
Author: Sven Fritsch
Author-email: sven@fritsch.io
License: UNKNOWN
Platform: UNKNOWN
Classifier: Programming Language :: Python :: 3
Classifier: License :: OSI Approved :: MIT License
Classifier: Operating System :: OS Independent
Classifier: Development Status :: 3 - Alpha
Classifier: Framework :: Django :: 2.1
Classifier: Framework :: Django :: 2.0
